nfe_parser/__init__.py
nfe_parser/cli.py
nfe_parser/nfe.py
nfe_parser/nfe_parser.py
nfe_parser-0.6.1.dist-info/AUTHORS.rst
nfe_parser-0.6.1.dist-info/LICENSE
nfe_parser-0.6.1.dist-info/METADATA
nfe_parser-0.6.1.dist-info/WHEEL
nfe_parser-0.6.1.dist-info/entry_points.txt
nfe_parser-0.6.1.dist-info/top_level.txt
nfe_parser-0.6.1.dist-info/RECORD
